culqi/__init__.py
culqi/client.py
culqi/version.py
culqi/resources/__init__.py
culqi/resources/base.py
culqi/resources/card.py
culqi/resources/charge.py
culqi/resources/customer.py
culqi/resources/event.py
culqi/resources/iin.py
culqi/resources/order.py
culqi/resources/plan.py
culqi/resources/refund.py
culqi/resources/subscription.py
culqi/resources/token.py
culqi/resources/transfer.py
culqi/utils/__init__.py
culqi/utils/errors.py
culqi/utils/status_codes.py
culqi/utils/urls.py
culqi2/__init__.py
culqi2/client.py
culqi2/version.py
culqi2/resources/__init__.py
culqi2/resources/base.py
culqi2/resources/card.py
culqi2/resources/charge.py
culqi2/resources/customer.py
culqi2/resources/event.py
culqi2/resources/iin.py
culqi2/resources/order.py
culqi2/resources/plan.py
culqi2/resources/refund.py
culqi2/resources/subscription.py
culqi2/resources/token.py
culqi2/resources/transfer.py
culqi2/utils/__init__.py
culqi2/utils/errors.py
culqi2/utils/status_codes.py
culqi2/utils/urls.py
culqi2-1.0.3.dist-info/LICENSE.txt
culqi2-1.0.3.dist-info/METADATA
culqi2-1.0.3.dist-info/WHEEL
culqi2-1.0.3.dist-info/top_level.txt
culqi2-1.0.3.dist-info/RECORD
