Metadata-Version: 2.1
Name: culqi2
Version: 1.0.3
Summary: Biblioteca de Culqi en Python
Home-page: https://github.com/culqi/culqi
Download-URL: https://github.com/culqi/culqi/-/archive/1.0.3/culqi2-1.0.3.tar.gz
Author: Jordan Diaz Diaz
Keywords: Api Client,Payment Integration,Culqi,Python 3,Python 2
Classifier: Development Status :: 5 - Production/Stable
Classifier: Intended Audience :: Developers
Classifier: License :: OSI Approved :: MIT License
Classifier: Natural Language :: English
Classifier: Programming Language :: Python :: 2.7
Classifier: Programming Language :: Python :: 3.5
Classifier: Programming Language :: Python :: 3.6
Classifier: Programming Language :: Python :: 3.7
Classifier: Programming Language :: Python :: 3.8
Classifier: Topic :: Software Development :: Libraries :: Python Modules
Requires: requests
Requires: jsonschema
License-File: LICENSE.txt
Requires-Dist: requests
Requires-Dist: jsonschema
